rest_framework_nested/__init__.py
rest_framework_nested/py.typed
rest_framework_nested/relations.py
rest_framework_nested/routers.py
rest_framework_nested/serializers.py
rest_framework_nested/viewsets.py
rest_framework_nested/__pycache__/__init__.cpython-36.pyc
rest_framework_nested/__pycache__/__init__.cpython-37.pyc
rest_framework_nested/__pycache__/relations.cpython-36.pyc
rest_framework_nested/__pycache__/relations.cpython-37.pyc
rest_framework_nested/__pycache__/routers.cpython-36.pyc
rest_framework_nested/__pycache__/routers.cpython-37.pyc
rest_framework_nested/__pycache__/serializers.cpython-36.pyc
rest_framework_nested/__pycache__/serializers.cpython-37.pyc
rest_framework_nested/__pycache__/viewsets.cpython-36.pyc
rest_framework_nested/__pycache__/viewsets.cpython-37.pyc
rest_framework_nested/runtests/__init__.py
rest_framework_nested/runtests/runcoverage.py
rest_framework_nested/runtests/runtests.py
rest_framework_nested/runtests/settings.py
rest_framework_nested/runtests/urls.py
drf_nested_routers-0.94.1.dist-info/LICENSE
drf_nested_routers-0.94.1.dist-info/METADATA
drf_nested_routers-0.94.1.dist-info/WHEEL
drf_nested_routers-0.94.1.dist-info/top_level.txt
drf_nested_routers-0.94.1.dist-info/RECORD
